.long-description.html
README.rst
setup.py
src/collective/__init__.py
src/collective.behavior.discount.egg-info/PKG-INFO
src/collective.behavior.discount.egg-info/SOURCES.txt
src/collective.behavior.discount.egg-info/dependency_links.txt
src/collective.behavior.discount.egg-info/entry_points.txt
src/collective.behavior.discount.egg-info/namespace_packages.txt
src/collective.behavior.discount.egg-info/not-zip-safe
src/collective.behavior.discount.egg-info/requires.txt
src/collective.behavior.discount.egg-info/top_level.txt
src/collective/behavior/__init__.py
src/collective/behavior/discount/__init__.py
src/collective/behavior/discount/behavior.py
src/collective/behavior/discount/configure.zcml
src/collective/behavior/discount/interfaces.py
src/collective/behavior/discount/schema.py
src/collective/behavior/discount/docs/CONTRIBUTORS.rst
src/collective/behavior/discount/docs/CREDITS.rst
src/collective/behavior/discount/docs/HISTORY.rst
src/collective/behavior/discount/docs/INSTALL.rst
src/collective/behavior/discount/docs/LICENSE.rst
src/collective/behavior/discount/locales/collective.behavior.discount.pot
src/collective/behavior/discount/locales/fi/LC_MESSAGES/collective.behavior.discount.mo
src/collective/behavior/discount/locales/fi/LC_MESSAGES/collective.behavior.discount.po
src/collective/behavior/discount/profiles/default/metadata.xml
src/collective/behavior/discount/tests/__init__.py
src/collective/behavior/discount/tests/base.py
src/collective/behavior/discount/tests/test_Discount.py
src/collective/behavior/discount/tests/test_IDiscount.py
src/collective/behavior/discount/tests/test_setup.py