Metadata-Version: 1.1
Name: collective.behavior.discount
Version: 0.3
Summary: Behavior of discount related fields.
Home-page: https://github.com/collective/collective.behavior.discount/
Author: Taito Horiuchi
Author-email: taito.horiuchi@gmail.com
License: BSD
Platform: UNKNOWN
Classifier: Framework :: Plone
Classifier: Framework :: Plone :: 4.3
Classifier: License :: OSI Approved :: BSD License
Classifier: Programming Language :: Python
Classifier: Programming Language :: Python :: 2.7
